{
    "graph": {
        "(0, 1, 0, 1)": [
            1.0,
            0.32848674290123614
        ],
        "(2, 3, 1, 0)": [
            -1.0,
            0.5521351252266555
        ],
        "(2, 3, 1, 1)": [
            -0.46143378315876754,
            -3.141592653589793
        ],
        "(1, 2, 1, 0)": [
            -0.532915217757144,
            -3.002678780084743
        ],
        "(0, 3, 1, 0)": [
            -0.5357683007285101,
            2.279228771106617
        ],
        "(0, 2, 0, 1)": [
            -0.5508481621283807,
            1.1295158415881856
        ],
        "(0, 2, 1, 0)": [
            0.5570786000053229,
            -2.0328373843836642
        ],
        "(0, 1, 0, 0)": [
            0.598747831563609,
            -0.523909140949855
        ],
        "(1, 2, 0, 1)": [
            1.0,
            0.4609503445718142
        ],
        "(0, 1, 1, 1)": [
            -1.0,
            -0.06412939963760561
        ],
        "(2, 3, 0, 0)": [
            1.0,
            3.141592653589793
        ],
        "(1, 3, 1, 1)": [
            1.0,
            -0.9430770304432484
        ],
        "(1, 3, 0, 1)": [
            -1.0,
            -1.506446809338947
        ],
        "(1, 3, 0, 0)": [
            -1.0,
            -1.0595496276817837
        ],
        "(1, 2, 0, 0)": [
            -1.0,
            0.8792358371988582
        ],
        "(0, 3, 1, 1)": [
            -1.0,
            -3.141592653589793
        ],
        "(0, 3, 0, 1)": [
            1.0,
            -0.5318779197933963
        ],
        "(0, 2, 1, 1)": [
            -1.0,
            -1.1810766764178
        ],
        "(0, 2, 0, 0)": [
            -1.0,
            1.8493062138153469
        ],
        "(1, 3, 1, 0)": [
            -1.0,
            -1.4912881310100858
        ]
    },
    "loss": [
        0.08247898699126888,
        0.007383564411613253
    ],
    "seed": 3267316621,
    "history": [
        [
            0.05980111855663184,
            0.006826033387773656
        ],
        [
            0.06740880948654338,
            0.007385758244408902
        ],
        [
            0.07307650357272466,
            0.008475453562345137
        ],
        [
            0.08247898699126888,
            0.007383564411613253
        ]
    ]
}