{
    "graph": {
    "(2, 3, 0, 1)": 1.0,
    "(0, 3, 1, 0)": -1.0,
    "(0, 3, 0, 1)": 1.0,
    "(1, 3, 1, 0)": 1.0,
    "(0, 2, 0, 0)": 1.0,
    "(1, 2, 0, 1)": 1.0,
    "(0, 1, 1, 1)": -1.0
    },
    "loss": [
        0.33333333456935205
    ],
    "history": [
        [
            0.3333333445862707
        ],
        [
            0.33333362652604875
        ],
        [
            0.3333334456903418
        ],
        [
            0.33333346127453406
        ],
        [
            0.3333333758495886
        ],
        [
            0.33333337349141273
        ],
        [
            0.33333376826213995
        ],
        [
            0.33333334586794844
        ],
        [
            0.33333356200655556
        ],
        [
            0.33333337865512824
        ],
        [
            0.3333333548849779
        ],
        [
            0.3333333565008914
        ],
        [
            0.3333334277742434
        ],
        [
            0.3333333498594573
        ],
        [
            0.3333333524149216
        ],
        [
            0.3333333354876709
        ],
        [
            0.33333333456935205
        ]
    ]
}
